{
  "id": "cmp_006",
  "asset_a_id": "anchor_08_security_v2",
  "asset_b_id": "anchor_08_security_v1",
  "asset_a_path": "outputs/approved/anchor_08_security_v2.png",
  "asset_b_path": "outputs/approved/anchor_08_security_v1.png",
  "chosen": "b",
  "source": "human",
  "reasoning": "v1 has ship corridor background that adds context. v2 has clean grey background which is better for concept art isolation. Close call — v1 wins on environment but v2 on composition.",
  "criteria_scores": {},
  "rubric_citations": [],
  "reviewer": "human:mike",
  "reviewed_at": "2026-04-12T21:35:56.345Z"
}